rest_rpc/__init__.py
rest_rpc/api_client.py
rest_rpc/api_definition.py
rest_rpc/api_implementation.py
rest_rpc/request_params.py
rest_rpc/route.py
rest_rpc-0.1.3.dist-info/licenses/LICENSE
rest_rpc-0.1.3.dist-info/WHEEL
rest_rpc-0.1.3.dist-info/METADATA
rest_rpc-0.1.3.dist-info/RECORD
