Metadata-Version: 2.4
Name: rest-rpc
Version: 0.1.3
Summary: A Python library that makes type-checked REST APIs easy
Author: Ruben Felgenhauer
Author-email: Ruben Felgenhauer <Ruben.Felgenhauer@posteo.de>
License-Expression: MIT
License-File: LICENSE
Requires-Dist: pydantic==2.10.6
Requires-Dist: pydantic-core==2.27.2
Requires-Dist: aiohttp>=3.13.3 ; extra == 'aiohttp'
Requires-Dist: fastapi[standard]>=0.128.0 ; extra == 'fastapi'
Requires-Dist: httpx>=0.28.1 ; extra == 'httpx'
Requires-Dist: requests>=2.32.5 ; extra == 'requests'
Requires-Dist: urllib3>=2.6.2 ; extra == 'urllib3'
Requires-Python: >=3.12
Project-URL: Documentation, https://github.com/felsenhower/rest-rpc/blob/main/docs/docs.md
Project-URL: Issue tracker, https://github.com/felsenhower/rest-rpc/issues
Project-URL: Source, https://github.com/felsenhower/rest-rpc
Provides-Extra: aiohttp
Provides-Extra: fastapi
Provides-Extra: httpx
Provides-Extra: requests
Provides-Extra: urllib3
